jupyterlab_plugin_playground/__init__.py
jupyterlab_plugin_playground/_version.py
jupyterlab_plugin_playground/labextension/build_log.json
jupyterlab_plugin_playground/labextension/package.json
jupyterlab_plugin_playground/labextension/schemas/@jupyterlab/plugin-playground/package.json.orig
jupyterlab_plugin_playground/labextension/schemas/@jupyterlab/plugin-playground/plugin.json
jupyterlab_plugin_playground/labextension/static/lib_index_js.c86e055e8ccff1c4543c.js
jupyterlab_plugin_playground/labextension/static/lib_index_js.c86e055e8ccff1c4543c.js.map
jupyterlab_plugin_playground/labextension/static/remoteEntry.7f92bd4579c54380c9c5.js
jupyterlab_plugin_playground/labextension/static/remoteEntry.7f92bd4579c54380c9c5.js.map
jupyterlab_plugin_playground/labextension/static/style.js
jupyterlab_plugin_playground/labextension/static/style_index_js.83a1708323667960666c.js
jupyterlab_plugin_playground/labextension/static/style_index_js.83a1708323667960666c.js.map
jupyterlab_plugin_playground/labextension/static/vendors-node_modules_css-loader_dist_runtime_api_js-node_modules_css-loader_dist_runtime_cssW-72eba1.ef0e828354f46079bf57.js
jupyterlab_plugin_playground/labextension/static/vendors-node_modules_css-loader_dist_runtime_api_js-node_modules_css-loader_dist_runtime_cssW-72eba1.ef0e828354f46079bf57.js.map
jupyterlab_plugin_playground/labextension/static/vendors-node_modules_jupyter-widgets_base_lib_index_js.314c6caaf7cca3873e78.js
jupyterlab_plugin_playground/labextension/static/vendors-node_modules_jupyter-widgets_base_lib_index_js.314c6caaf7cca3873e78.js.map
jupyterlab_plugin_playground/labextension/static/vendors-node_modules_lumino_datagrid_dist_index_es6_js-node_modules_raw-loader_dist_cjs_js_no-e13caa.76c656a6faa161546a2b.js
jupyterlab_plugin_playground/labextension/static/vendors-node_modules_lumino_datagrid_dist_index_es6_js-node_modules_raw-loader_dist_cjs_js_no-e13caa.76c656a6faa161546a2b.js.map
jupyterlab_plugin_playground-0.4.0.dist-info/LICENSE
jupyterlab_plugin_playground-0.4.0.dist-info/METADATA
jupyterlab_plugin_playground-0.4.0.dist-info/WHEEL
jupyterlab_plugin_playground-0.4.0.dist-info/top_level.txt
jupyterlab_plugin_playground-0.4.0.dist-info/RECORD
